nnieqat/__init__.py
nnieqat/cuda10/__init__.py
nnieqat/cuda10/quantize.py
nnieqat/gpu/__init__.py
nnieqat/gpu/quantize.py
nnieqat/gpu/lib/gfpq.dll
nnieqat/gpu/lib/gfpq.lib
nnieqat/gpu/lib/libgfpq.a
nnieqat/gpu/lib/libgfpq.so
nnieqat/gpu/lib/libgfpq.so.1
nnieqat/gpu/lib/libgfpq.so.1.1.5
nnieqat/gpu/lib/libgfpq_gpu.a
nnieqat/gpu/lib/libgfpq_gpu.so
nnieqat/gpu/lib/libgfpq_gpu.so.1
nnieqat/gpu/lib/libgfpq_gpu.so.1.1.5
nnieqat/modules/__init__.py
nnieqat/modules/conv.py
nnieqat/modules/linear.py
nnieqat/modules/pooling.py
nnieqat-0.1.0b0.dist-info/LICENSE.txt
nnieqat-0.1.0b0.dist-info/METADATA
nnieqat-0.1.0b0.dist-info/WHEEL
nnieqat-0.1.0b0.dist-info/top_level.txt
nnieqat-0.1.0b0.dist-info/RECORD
