Metadata-Version: 2.1
Name: nnieqat
Version: 0.1.0b0
Summary: A nnie quantization aware training tool on pytorch.
Home-page: https://github.com/aovoc/nnieqat-pytorch
Author: Minqin Chen
Author-email: minqinchen@deepglint.com
License: MIT
Keywords: quantization aware training,deep learning,neural network,CNN,machine learning
Platform: UNKNOWN
Classifier: Development Status :: 3 - Alpha
Classifier: Intended Audience :: Science/Research
Classifier: Intended Audience :: Developers
Classifier: Topic :: Scientific/Engineering :: Artificial Intelligence
Classifier: Topic :: Software Development :: Libraries :: Python Modules
Classifier: License :: OSI Approved :: MIT License
Classifier: Programming Language :: Python :: 3
Classifier: Programming Language :: Python :: 3.5
Classifier: Programming Language :: Python :: 3.6
Classifier: Programming Language :: Python :: 3.7
Classifier: Programming Language :: Python :: 3.8
Classifier: Programming Language :: Python :: 3 :: Only
Requires-Python: >=3.5, <4
Requires-Dist: torch (>=1.0)
Requires-Dist: numba (>=0.42.0)
Requires-Dist: numpy (>=1.18.1)
Provides-Extra: test
Requires-Dist: torchvision (>=0.4) ; extra == 'test'
